Coolapk/Exception.py
Coolapk/__init__.py
Coolapk/application.py
Coolapk/function.py
Coolapk/object.py
Coolapk/utils/__init__.py
Coolapk/utils/login.py
Coolapk-0.0.3.dist-info/LICENSE
Coolapk-0.0.3.dist-info/METADATA
Coolapk-0.0.3.dist-info/WHEEL
Coolapk-0.0.3.dist-info/top_level.txt
Coolapk-0.0.3.dist-info/RECORD
